{
  "id": 50,
  "name": "Kanji Unit 20B & 24",
  "tags": [
    "LAJ 3"
  ],
  "cards": [
    {
      "id": 0,
      "word": "この歌の意味がよくわからない",
      "ans": "このうたのいみがよくわからない",
      "remarks": ""
    },
    {
      "id": 1,
      "word": "天気が悪いから、今日は海に行かない",
      "ans": "てんきがわるいから、きょうはうみにいかない",
      "remarks": ""
    },
    {
      "id": 2,
      "word": "去年の試験の問題と答えは図書館にある",
      "ans": "きょねんのしけんのもんだいとこたえはとしょかんにある",
      "remarks": ""
    },
    {
      "id": 3,
      "word": "兄は時計を集めている",
      "ans": "あにはとけいをあつめている",
      "remarks": ""
    },
    {
      "id": 4,
      "word": "来年から新しい研究を始める",
      "ans": "らいねんからあたらしいけんきゅうをはじめる",
      "remarks": ""
    },
    {
      "id": 5,
      "word": "1日考えたけど、この問題がわからない",
      "ans": "いちにちかんがえたけど、このもんだいがわからない",
      "remarks": ""
    },
    {
      "id": 6,
      "word": "音が大きくて、耳がいたくなった",
      "ans": "おとがおおきくて、みみがいたくなった",
      "remarks": ""
    },
    {
      "id": 7,
      "word": "パソコンが2台あるから、弟に1台貸した",
      "ans": "パソコンが2だいあるから、おとうとに1だいかした",
      "remarks": ""
    },
    {
      "id": 8,
      "word": "今日は用事があるから早く帰る",
      "ans": "きょうはようじがあるから、はやくかえる",
      "remarks": ""
    }
  ]
}